postal_admin_client/__init__.py
postal_admin_client/client.py
postal_admin_client/httpclient.py
postal_admin_client/utils.py
postal_admin_client-0.1.1.dist-info/LICENSE
postal_admin_client-0.1.1.dist-info/METADATA
postal_admin_client-0.1.1.dist-info/WHEEL
postal_admin_client-0.1.1.dist-info/top_level.txt
postal_admin_client-0.1.1.dist-info/RECORD
