Metadata-Version: 2.1
Name: postal-admin-client
Version: 0.1.1
Summary: Python admin client for the open source mail delivery platform Postal
Home-page: https://github.com/ZettaIO/postal-admin-client
Author: Einar Forselv
Author-email: eforselv@gmail.com
License: UNKNOWN
Keywords: posta,admin,client
Platform: UNKNOWN
Classifier: Programming Language :: Python
Classifier: Programming Language :: Python :: 3
Classifier: Programming Language :: Python :: 3.6
Classifier: Programming Language :: Python :: 3.7
Requires-Dist: requests (>=2.22)
Requires-Dist: beautifulsoup4 (>=4.7)
